__init__.py
fmconsult/__init__.py
fmconsult/mailerapi/__init__.py
fmconsult/mailerapi/api.py
fmconsult/mailerapi/apis/__init__.py
fmconsult/mailerapi/apis/emails.py
fmconsult/mailerapi/dtos/__init__.py
fmconsult/mailerapi/dtos/email.py
fmconsult_mailer_api_python_sdk-1.0.0.dist-info/licenses/LICENSE
fmconsult_mailer_api_python_sdk-1.0.0.dist-info/METADATA
fmconsult_mailer_api_python_sdk-1.0.0.dist-info/WHEEL
fmconsult_mailer_api_python_sdk-1.0.0.dist-info/top_level.txt
fmconsult_mailer_api_python_sdk-1.0.0.dist-info/RECORD
